CHANGELOG.md
configparserenhanced/ConfigParserEnhanced.py
configparserenhanced/Debuggable.py
configparserenhanced/ExceptionControl.py
configparserenhanced/HandlerParameters.py
configparserenhanced/TypedProperty.py
configparserenhanced/__init__.py
configparserenhanced/unittests/__init__.py
configparserenhanced/unittests/common.py
configparserenhanced/unittests/config_test_configparserenhanced.ini
configparserenhanced/unittests/config_test_configparserenhanced_badkeys.ini
configparserenhanced/unittests/config_test_configparserenhanced_default.ini
configparserenhanced/unittests/config_test_configparserenhanced_validation_01.ini
configparserenhanced/unittests/config_test_configparserenhanced_validation_02.ini
configparserenhanced/unittests/config_test_configparserenhanced_validation_03a.ini
configparserenhanced/unittests/config_test_configparserenhanced_validation_03b.ini
configparserenhanced/unittests/test_ConfigParserEnhanced.py
configparserenhanced/unittests/test_Debuggable.py
configparserenhanced/unittests/test_ExceptionControl.py
configparserenhanced/unittests/test_HandlerParameters.py
configparserenhanced/unittests/test_TypedProperty.py
configparserenhanced/version.py
configparserenhanced-0.8.1.5.dist-info/LICENSE
configparserenhanced-0.8.1.5.dist-info/METADATA
configparserenhanced-0.8.1.5.dist-info/WHEEL
configparserenhanced-0.8.1.5.dist-info/RECORD
