Metadata-Version: 2.1
Name: configparserenhanced
Version: 0.8.1.5
Summary: A tool that extends configparser to enable enhanced processing of .ini files.
Home-page: https://github.com/sandialabs/ConfigParserEnhanced
License: LICENSE
Keywords: Utility,Bash,Configuration,ConfigParserEnhanced,ConfigParser
Author: William McLendon
Author-email: wcmclen@sandia.gov
Requires-Python: >=3.6,<4.0
Classifier: Development Status :: 5 - Production/Stable
Classifier: Intended Audience :: Developers
Classifier: Intended Audience :: Other Audience
Classifier: Intended Audience :: System Administrators
Classifier: License :: OSI Approved :: BSD License
Classifier: License :: Other/Proprietary License
Classifier: Programming Language :: Python :: 3
Classifier: Programming Language :: Python :: 3.6
Classifier: Programming Language :: Python :: 3.7
Classifier: Programming Language :: Python :: 3.8
Classifier: Programming Language :: Python :: 3.9
Classifier: Programming Language :: Python :: 3.10
Classifier: Programming Language :: Python :: 3.11
Classifier: Programming Language :: Python :: 3 :: Only
Project-URL: CI, https://github.com/sandialabs/ConfigParserEnhanced/actions/workflows/test-driver-core.yml
Project-URL: Documentation, https://configparserenhanced.readthedocs.io/en/latest/
Project-URL: Issues, https://github.com/sandialabs/ConfigParserEnhanced/issues
Project-URL: Repository, https://github.com/sandialabs/ConfigParserEnhanced
